{
  "app": {
    "signingConfigs": [
      {
        "name": "default",
        "type": "HarmonyOS",
        "material": {
          "certpath": "/Users/xiaoan/.ohos/config/default_harmonyos_KNZC_iLyUm8Ft4SWrp6K8DoOGQkYc8ntF9bCZZTyJmU=.cer",
          "keyAlias": "debugKey",
          "keyPassword": "0000001ACE693A7591563C2E1CFAEC13784B773E96D605F7158947A04095817E640B44E19BE48769B3EB",
          "profile": "/Users/xiaoan/.ohos/config/default_harmonyos_KNZC_iLyUm8Ft4SWrp6K8DoOGQkYc8ntF9bCZZTyJmU=.p7b",
          "signAlg": "SHA256withECDSA",
          "storeFile": "/Users/xiaoan/.ohos/config/default_harmonyos_KNZC_iLyUm8Ft4SWrp6K8DoOGQkYc8ntF9bCZZTyJmU=.p12",
          "storePassword": "0000001A49514E5B3A38F1C2506DA4BAB797EFF2ADA040B14718211560CDE4AEE434BE6177D79C9A3C55"
        }
      }
    ],
    "products": [
      {
        "name": "default",
        "signingConfig": "default",
        "compatibleSdkVersion": "6.1.0(23)",
        "runtimeOS": "HarmonyOS",
        "buildOption": {},
        "targetSdkVersion": "6.1.0(23)",
        "compileSdkVersion": "6.1.0(23)"
      }
    ],
    "buildModeSet": [
      {
        "name": "debug"
      },
      {
        "name": "release"
      }
    ]
  },
  "modules": [
    {
      "name": "entry",
      "srcPath": "./entry",
      "targets": [
        {
          "name": "default",
          "applyToProducts": [
            "default"
          ]
        }
      ]
    }
  ]
}
